LICENSE
MANIFEST.in
README.rst
setup.py
sheetparser/__init__.py
sheetparser/documents.py
sheetparser/patterns.py
sheetparser/results.py
sheetparser/utils.py
sheetparser.egg-info/PKG-INFO
sheetparser.egg-info/SOURCES.txt
sheetparser.egg-info/dependency_links.txt
sheetparser.egg-info/requires.txt
sheetparser.egg-info/top_level.txt
sheetparser/backends/__init__.py
sheetparser/backends/_array.py
sheetparser/backends/_openpyxl.py
sheetparser/backends/_pdfminer.py
sheetparser/backends/_win32com.py
sheetparser/backends/_xlrd.py
sheetparser/backends/pdf_extract.py
sheetparser/backends/pdf_util1.py
sheetparser/backends/pdf_utils2.py
sheetparser/tests/__init__.py
sheetparser/tests/test_sheetparser.py
sheetparser/tests/test_table1.xlsx