Metadata-Version: 1.1
Name: sheetparser
Version: 0.2
Summary: Turns an Excel (or pdf, csv...) workbook made of sheets containing several tables into a usable source of data
Home-page: http://github.com/gcoffin/sheetparser
Author: Guillaume Coffin
Author-email: guill.coffin@gmail.com
License: GPLv3
Download-URL: https://github.com/gcoffin/sheetparser/archive/0.2.tar.gz
Keywords: excel tables parsing
Platform: UNKNOWN
Classifier: Development Status :: 4 - Beta
Classifier: Intended Audience :: Developers
Classifier: License :: OSI Approved :: GNU General Public License v3 (GPLv3)
Classifier: Programming Language :: Python :: 2.7
Classifier: Programming Language :: Python :: 3
Classifier: Operating System :: MacOS :: MacOS X
Classifier: Operating System :: Microsoft :: Windows
Classifier: Operating System :: POSIX
